django_toolbox-0.2.dist-info/DESCRIPTION.rst
django_toolbox-0.2.dist-info/METADATA
django_toolbox-0.2.dist-info/RECORD
django_toolbox-0.2.dist-info/WHEEL
django_toolbox-0.2.dist-info/metadata.json
django_toolbox-0.2.dist-info/top_level.txt
toolbox/__init__.py
toolbox/choices.py
toolbox/claude.py
toolbox/emails.py
toolbox/fields.py
toolbox/forms.py
toolbox/formsetfield.py
toolbox/messages.py
toolbox/next.py
toolbox/text.py
toolbox/tokens.py
toolbox/wrappedpartial.py
toolbox/templatetags/__init__.py
toolbox/templatetags/b-utils.py
toolbox/templatetags/ballot.py
toolbox/templatetags/bfield.py
toolbox/templatetags/claude.py
toolbox/templatetags/toolbox.py
