Metadata-Version: 2.0
Name: django-toolbox
Version: 0.2
Summary: A collection of utilities for django applications.
Home-page: https://github.com/bmispelon/django-toolbox
Author: Baptiste Mispelon
Author-email: bmispelon@gmail.com
License: BSD
Keywords: django
Platform: UNKNOWN
Classifier: Programming Language :: Python
Classifier: Topic :: Software Development :: Libraries :: Python Modules
Classifier: Framework :: Django
Classifier: Environment :: Web Environment
